Code/flopr/asynchronous/src/flopr2.sv
`timescale 1ns/1ps

//Ex.A.21 Resettable Register (Asynchronous reset)
module flopr2
       #(parameter w = 2)
       (input logic clk,
       input logic reset,
       input logic [w-1:0] d,
       output logic [w-1:0] q);

       // Asynchronous reset (clock should be positive, and reset negative to avoid error) [eventriger]
       always_ff @(posedge clk, posedge reset)
        if (reset) q <= 2'b0;       //using 2 bits
        else q <= d;
endmodule

Code/flopr/asynchronous/flopr2.vcd
$date
	Fri Aug 27 15:22:56 2021
$end
$version
	Icarus Verilog
$end
$timescale
	1ps
$end
$scope module flopr2 $end
$var wire 1 ! clk $end
$var wire 2 " d [1:0] $end
$var wire 1 # reset $end
$var reg 2 $ q [1:0] $end
$upscope $end
$enddefinitions $end
#0
$dumpvars
b1 $
0#
b1 "
1!
$end
#5000
0!
#10000
1!
#15000
b0 $
b11 "
1#
0!
#20000
1!
#25000
b1 "
0#
0!
#30000
b1 $
1!
#35000
b0 $
b11 "
1#
0!
#40000
1!
#45000
b10 "
0!
#50000
1!
#55000
b0 "
0#
0!
#60000
1!
#65000
b1 "
0!
#70000
b1 $
1!
#75000
b11 "
0!
#80000
b11 $
1!
#85000
b1 "
0!
#90000
b1 $
1!
#95000
b0 "
0!
#100000
b0 $
1!
#105000
b10 "
1#
0!
#110000
1!
#115000
0!
#120000
1!
#125000
b0 "
0!
#130000
1!
#135000
b1 "
0!
#140000
1!
#145000
b0 "
0#
0!
#150000
1!
#155000
1#
0!
#160000
1!
#165000
b1 "
0!
#170000
1!
#175000
0#
0!
#180000
b1 $
1!
#185000
b10 "
0!
#190000
b10 $
1!
