Code/flop/src/flop.sv
`timescale 1ns/1ps

//Ex.A.20 Register
module flop
       #(parameter w = 2)
       (input logic clk,
       input logic [w-1:0] d,
       output logic [w-1:0] q);

       always_ff @(posedge clk)
        q <= d;
endmodule

Code/flop/flop.vcd
$date
	Sat Aug 28 22:07:33 2021
$end
$version
	Icarus Verilog
$end
$timescale
	1ps
$end
$scope module flop $end
$var wire 1 ! clk $end
$var wire 2 " d [1:0] $end
$var reg 2 # q [1:0] $end
$upscope $end
$enddefinitions $end
#0
$dumpvars
b10 #
b10 "
1!
$end
#5000
0!
#10000
1!
#15000
b11 "
0!
#20000
b11 #
1!
#25000
b10 "
0!
#30000
b10 #
1!
#35000
b11 "
0!
#40000
b11 #
1!
#45000
0!
#50000
1!
#55000
b0 "
0!
#60000
b0 #
1!
#65000
b11 "
0!
#70000
b11 #
1!
#75000
b10 "
0!
#80000
b10 #
1!
#85000
b0 "
0!
#90000
b0 #
1!
#95000
b11 "
0!
#100000
b11 #
1!
#105000
b10 "
0!
#110000
b10 #
1!
#115000
b1 "
0!
#120000
b1 #
1!
#125000
0!
#130000
1!
#135000
b11 "
0!
#140000
b11 #
1!
#145000
b0 "
0!
#150000
b0 #
1!
#155000
b10 "
0!
#160000
b10 #
1!
#165000
0!
#170000
1!
#175000
b11 "
0!
#180000
b11 #
1!
