Code/gates/src/gates.sv
`timescale 1ns/1ps

//EX.A.4 Logic Gates
module gates
       #(parameter w = 2)
       (input logic [w-1:0] a, b,
       output logic [w-1:0] y1, y2, y3, y4, y5);

       /* Five different two-input logic
       * gates acting on #-bit busses*/
       assign y1 = a & b;  //AND
       assign y2 = a | b;  //OR
       assign y3 = a ^ b;  //XOR
       assign y4 = ~(a & b);  //NAND
       assign y5 = ~(a | b);  //NOR
endmodule

Code/gates/gates.vcd
$date
	Sat Aug 28 15:31:02 2021
$end
$version
	Icarus Verilog
$end
$timescale
	1ps
$end
$scope module gates $end
$var wire 2 ! a [1:0] $end
$var wire 2 " b [1:0] $end
$var wire 2 # y1 [1:0] $end
$var wire 2 $ y2 [1:0] $end
$var wire 2 % y3 [1:0] $end
$var wire 2 & y4 [1:0] $end
$var wire 2 ' y5 [1:0] $end
$upscope $end
$enddefinitions $end
#0
$dumpvars
b1 '
b1 &
b0 %
b10 $
b10 #
b10 "
b10 !
$end
#2001
b11 &
b0 '
b0 #
b11 $
b11 %
b0 !
b11 "
#4001
b1 &
b1 '
b10 #
b10 $
b0 %
b10 !
b10 "
#6001
b11 &
b0 #
b10 %
b0 !
#8001
b10 !
b0 "
#10001
b11 '
b0 $
b0 %
b0 !
#12001
b10 &
b0 '
b1 #
b11 $
b10 %
b11 !
b1 "
#14001
b11 &
b11 '
b0 #
b0 $
b0 %
b0 !
b0 "
#16001
b1 '
b10 $
b10 %
b10 !
#18001
b10 &
b0 '
b1 #
b11 $
b11 !
b1 "
#20001
b11 &
b10 '
b0 #
b1 $
b1 %
b0 !
#24001
b1 !
b0 "
#26001
b1 &
b0 '
b10 #
b11 $
b11 !
b10 "
#28001
b11 &
b10 '
b0 #
b1 $
b0 !
b1 "
#32001
b1 &
b1 '
b10 #
b10 $
b0 %
b10 !
b10 "
#34001
b11 &
b0 '
b0 #
b11 $
b11 %
b1 "
#36001
b1 &
b1 '
b10 #
b10 $
b0 %
b10 "
#38001
b10 &
b10 '
b1 #
b1 $
b1 !
b1 "
#40001
b11 &
b1 '
b0 #
b10 $
b10 %
b10 !
b0 "
