Code/flopr/src/flopr.sv
`timescale 1ns/1ps

//Ex.A.21 Resettable Register (Synchronous reset)
module flopr
       #(parameter w = 2)
       (input logic clk,
       input logic reset,
       input logic [w-1:0] d,
       output logic [w-1:0] q);

       // Synchronous reset
       always_ff @(posedge clk)
        if (reset) q <= 2'b0;       //using 2 bits
        else q <= d;
endmodule

Code/flopr/synchronous/flopr.vcd
$date
	Fri Aug 27 15:23:14 2021
$end
$version
	Icarus Verilog
$end
$timescale
	1ps
$end
$scope module flopr $end
$var wire 1 ! clk $end
$var wire 2 " d [1:0] $end
$var wire 1 # reset $end
$var reg 2 $ q [1:0] $end
$upscope $end
$enddefinitions $end
#0
$dumpvars
b0 $
1#
b1 "
1!
$end
#5000
b11 "
0!
#10000
1!
#15000
b0 "
0#
0!
#20000
1!
#25000
b11 "
1#
0!
#30000
1!
#35000
b1 "
0!
#40000
1!
#45000
b0 "
0#
0!
#50000
1!
#55000
b1 "
1#
0!
#60000
1!
#65000
b11 "
0#
0!
#70000
b11 $
1!
#75000
b10 "
1#
0!
#80000
b0 $
1!
#85000
b0 "
0!
#90000
1!
#95000
b11 "
0!
#100000
1!
#105000
b1 "
0!
#110000
1!
#115000
0!
#120000
1!
#125000
b10 "
0#
0!
#130000
b10 $
1!
#135000
0!
#140000
1!
#145000
b11 "
1#
0!
#150000
b0 $
1!
#155000
0#
0!
#160000
b11 $
1!
#165000
b10 "
0!
#170000
b10 $
1!
#175000
b1 "
0!
#180000
b1 $
1!
#185000
b10 "
1#
0!
#190000
b0 $
1!
